{
  "user": {
    "id": "usr_demo_01",
    "displayName": "Jordan",
    "email": "jordan@example.com",
    "pregnancyWeek": 18,
    "dueDate": "2026-08-12"
  },
  "checkInProgress": {
    "checkInsThisWeek": 4,
    "weeklyGoal": 7,
    "streakDays": 5,
    "totalCheckIns": 31,
    "lastCheckInAt": "2026-04-02T08:15:00Z",
    "lastMoodLabel": "Calm"
  },
  "socialCounts": {
    "followers": 42,
    "following": 18
  },
  "babySize": {
    "weekReferenced": 18,
    "headline": "Your baby is about the size of a bell pepper",
    "supportingCopy": "Many parents find this week brings clearer little kicks — every pregnancy unfolds at its own pace.",
    "emoji": "🫑",
    "illustrationUrl": null,
    "illustrationAlt": "Placeholder for a gentle fruit comparison illustration"
  }
}
